{
  "sections": {
    "main": {
      "type": "main-page",
      "settings": {
        "content_width": "100ch"
      }
    },
    "multi_column_Vej8qr": {
      "type": "multi-column",
      "blocks": {
        "item_99jCHi": {
          "type": "item",
          "settings": {
            "image": "shopify:\/\/shop_images\/our_content-authors-image-1400x1000.jpg",
            "column_size": "4",
            "title": "Authors",
            "heading_tag": "h4",
            "content": "<p>From world famous to up and coming authors, we work hard to create our catalogue.<\/p>",
            "link_url": "shopify:\/\/pages\/audiobook-authors",
            "link_text": "Browse authors",
            "link_style": "button"
          }
        },
        "item_TG4AWt": {
          "type": "item",
          "settings": {
            "image": "shopify:\/\/shop_images\/our_content-narrators-image-1400x1000.jpg",
            "column_size": "4",
            "title": "Narrators",
            "heading_tag": "h4",
            "content": "<p>The narrator is so important. See who narrates our library.<\/p>",
            "link_url": "shopify:\/\/pages\/audiobook-narrators",
            "link_text": "Browse narrators",
            "link_style": "button"
          }
        },
        "item_6PhWpF": {
          "type": "item",
          "settings": {
            "image": "shopify:\/\/shop_images\/our_content-titles-image-1400x1000.jpg",
            "column_size": "4",
            "title": "Titles",
            "heading_tag": "h4",
            "content": "<p>We have a growing library of audiobooks. Browse the whole catalogue here.<\/p>",
            "link_url": "shopify:\/\/pages\/audiobooks",
            "link_text": "Audiobooks",
            "link_style": "button"
          }
        },
        "item_Gdcabp": {
          "type": "item",
          "settings": {
            "image": "shopify:\/\/shop_images\/our_content-overview-image-1400x1000.jpg",
            "column_size": "4",
            "title": "Overviews",
            "heading_tag": "h4",
            "content": "<p>Read in more detail about many of our titles with our overviews of what each story is about.<\/p>",
            "link_url": "shopify:\/\/pages\/overviews",
            "link_text": "Overviews",
            "link_style": "button"
          }
        },
        "item_87nc3r": {
          "type": "item",
          "settings": {
            "image": "shopify:\/\/shop_images\/our_content-audiogram-image-1400x1000.jpg",
            "column_size": "4",
            "title": "Audiogrammes",
            "heading_tag": "h4",
            "content": "<p>Read along as you listen to the extract from the audiobook.<\/p>",
            "link_url": "shopify:\/\/pages\/audiogrammes",
            "link_text": "Audiogrammes",
            "link_style": "button"
          }
        },
        "item_G7wtqq": {
          "type": "item",
          "settings": {
            "image": "shopify:\/\/shop_images\/our_content-series-image-1400x1000.jpg",
            "column_size": "4",
            "title": "Series",
            "heading_tag": "h4",
            "content": "<p>Books come in series. Liked the first? Love the rest!<\/p>",
            "link_url": "shopify:\/\/pages\/audiobook-series",
            "link_text": "Series",
            "link_style": "button"
          }
        },
        "item_rp3DUi": {
          "type": "item",
          "settings": {
            "image": "shopify:\/\/shop_images\/green-and-white-marbled-coloring.jpg",
            "column_size": "3",
            "title": "Characters",
            "heading_tag": "h4",
            "content": "<p>Read about your favourites characters from much loved stories.<\/p>",
            "link_url": "shopify:\/\/pages\/audiobook-characters",
            "link_text": "Characters",
            "link_style": "button"
          }
        }
      },
      "block_order": [
        "item_99jCHi",
        "item_TG4AWt",
        "item_6PhWpF",
        "item_Gdcabp",
        "item_87nc3r",
        "item_G7wtqq",
        "item_rp3DUi"
      ],
      "settings": {
        "full_width": false,
        "stack_on_mobile": true,
        "gap": "medium",
        "text_alignment": "start",
        "subheading": "Audiobook resources",
        "title": "Explore our library",
        "content": "<p>Our library of audiobooks is growing all the time. Browse in multiple ways the entire catalogue.<\/p>",
        "background": "",
        "background_gradient": "",
        "text_color": ""
      }
    },
    "collection_list_LXeRzF": {
      "type": "collection-list",
      "blocks": {
        "collection_3hHUG6": {
          "type": "collection",
          "settings": {
            "collection": "audiobooks-8-10-years",
            "subheading": "",
            "title": "",
            "url": "",
            "heading_tag": "h4",
            "text_position": "place-self-end text-end",
            "text_color": "#ffffff",
            "overlay_color": "#000000",
            "overlay_opacity": 30
          }
        },
        "collection_abWHLk": {
          "type": "collection",
          "settings": {
            "collection": "audiobooks-10-to-teens",
            "subheading": "",
            "title": "",
            "url": "",
            "heading_tag": "h4",
            "text_position": "place-self-end text-end",
            "text_color": "#ffffff",
            "overlay_color": "#000000",
            "overlay_opacity": 30
          }
        },
        "collection_a3gj4V": {
          "type": "collection",
          "settings": {
            "collection": "audiobooks-5-8-years",
            "subheading": "",
            "title": "",
            "url": "",
            "heading_tag": "h4",
            "text_position": "place-self-end text-end",
            "text_color": "#ffffff",
            "overlay_color": "#000000",
            "overlay_opacity": 30
          }
        },
        "collection_aLY3QG": {
          "type": "collection",
          "settings": {
            "collection": "voxblock-audiobooks-under-5s",
            "subheading": "",
            "title": "",
            "url": "",
            "heading_tag": "h4",
            "text_position": "place-self-end text-end",
            "text_color": "#ffffff",
            "overlay_color": "#000000",
            "overlay_opacity": 30
          }
        }
      },
      "block_order": [
        "collection_3hHUG6",
        "collection_abWHLk",
        "collection_a3gj4V",
        "collection_aLY3QG"
      ],
      "settings": {
        "full_width": true,
        "stack_collections": true,
        "collections_per_row": 5,
        "show_progress_bar": false,
        "subheading": "Browse by",
        "title": "Age group",
        "content": "",
        "link_url": "",
        "link_text": "",
        "background": "",
        "background_gradient": "",
        "text_color": "",
        "heading_color": "",
        "heading_gradient": ""
      }
    },
    "collection_list_Tx3KgY": {
      "type": "collection-list",
      "blocks": {
        "collection_jwEHQ7": {
          "type": "collection",
          "settings": {
            "collection": "childrens-action-audiobooks",
            "subheading": "",
            "title": "",
            "url": "",
            "heading_tag": "h4",
            "text_position": "place-self-end text-end",
            "text_color": "#ffffff",
            "overlay_color": "#000000",
            "overlay_opacity": 30
          }
        },
        "collection_XBEqVR": {
          "type": "collection",
          "settings": {
            "collection": "childrens-bedtime-calm-audiobooks",
            "subheading": "",
            "title": "",
            "url": "",
            "heading_tag": "h4",
            "text_position": "place-self-end text-end",
            "text_color": "#ffffff",
            "overlay_color": "#000000",
            "overlay_opacity": 30
          }
        },
        "collection_T7tQLd": {
          "type": "collection",
          "settings": {
            "collection": "childrens-facts-and-learning-audiobooks",
            "subheading": "",
            "title": "",
            "url": "",
            "heading_tag": "h4",
            "text_position": "place-self-end text-end",
            "text_color": "#ffffff",
            "overlay_color": "#000000",
            "overlay_opacity": 30
          }
        },
        "collection_GhQwgE": {
          "type": "collection",
          "settings": {
            "collection": "childrens-family-favourites-audiobooks",
            "subheading": "",
            "title": "",
            "url": "",
            "heading_tag": "h4",
            "text_position": "place-self-end text-end",
            "text_color": "#ffffff",
            "overlay_color": "#000000",
            "overlay_opacity": 30
          }
        },
        "collection_CfVzkk": {
          "type": "collection",
          "settings": {
            "collection": "childrens-musical-stories-audiobooks",
            "subheading": "",
            "title": "",
            "url": "",
            "heading_tag": "h4",
            "text_position": "place-self-end text-end",
            "text_color": "#ffffff",
            "overlay_color": "#000000",
            "overlay_opacity": 30
          }
        }
      },
      "block_order": [
        "collection_jwEHQ7",
        "collection_XBEqVR",
        "collection_T7tQLd",
        "collection_GhQwgE",
        "collection_CfVzkk"
      ],
      "settings": {
        "full_width": true,
        "stack_collections": true,
        "collections_per_row": 3,
        "show_progress_bar": false,
        "subheading": "Browse by",
        "title": "Theme",
        "content": "",
        "link_url": "",
        "link_text": "View all",
        "background": "",
        "background_gradient": "",
        "text_color": "",
        "heading_color": "",
        "heading_gradient": ""
      }
    }
  },
  "order": [
    "main",
    "multi_column_Vej8qr",
    "collection_list_LXeRzF",
    "collection_list_Tx3KgY"
  ]
}
